Metadata-Version: 1.1
Name: django-simple-rest
Version: 1.3.0
Summary: A drop dead simple package for creating RESTful APIs on top of Django
Home-page: https://github.com/freshplum/django-simple-rest
Author: Christopher Roach
Author-email: croach@freshplum.com
License: UNKNOWN
Keywords: rest,django,api
Platform: UNKNOWN
Classifier: Development Status :: 3 - Alpha
Classifier: Environment :: Web Environment
Classifier: Framework :: Django
Classifier: Intended Audience :: Developers
Classifier: License :: OSI Approved :: MIT License
Classifier: Operating System :: OS Independent
Classifier: Programming Language :: Python :: 2.6
Classifier: Programming Language :: Python :: 2.7
Classifier: Topic :: Internet :: WWW/HTTP
Classifier: Topic :: Internet :: WWW/HTTP :: Dynamic Content
Classifier: Topic :: Software Development :: Libraries :: Python Modules
